buildstock_fetch/__init__.py
buildstock_fetch/__main__.py
buildstock_fetch/main.py
buildstock_fetch/main_cli.py
buildstock_fetch-1.0.3.dist-info/licenses/LICENSE
buildstock_fetch-1.0.3.dist-info/METADATA
buildstock_fetch-1.0.3.dist-info/WHEEL
buildstock_fetch-1.0.3.dist-info/entry_points.txt
buildstock_fetch-1.0.3.dist-info/top_level.txt
buildstock_fetch-1.0.3.dist-info/RECORD
