Metadata-Version: 2.4
Name: buildstock-fetch
Version: 1.0.3
Summary: This library simplifies downloading building characteristics and load curve data from NREL's ResStock and ComStock projects.
Author-email: Switchbox <hello@switch.box>
Project-URL: Homepage, https://switchbox-data.github.io/buildstock-fetch/
Project-URL: Repository, https://github.com/switchbox-data/buildstock-fetch
Project-URL: Documentation, https://switchbox-data.github.io/buildstock-fetch/
Keywords: python
Classifier: Intended Audience :: Developers
Classifier: Programming Language :: Python
Classifier: Programming Language :: Python :: 3
Classifier: Programming Language :: Python :: 3.9
Classifier: Programming Language :: Python :: 3.10
Classifier: Programming Language :: Python :: 3.11
Classifier: Programming Language :: Python :: 3.12
Classifier: Programming Language :: Python :: 3.13
Classifier: Topic :: Software Development :: Libraries :: Python Modules
Requires-Python: <4.0,>=3.9
License-File: LICENSE
Requires-Dist: requests>=2.32.3
Requires-Dist: typer>=0.9.0
Requires-Dist: rich>=13.9.5
Requires-Dist: questionary>=1.11.0
Requires-Dist: polars>=0.20.0
Dynamic: license-file
